ghent_theft_module/cli.py
ghent_theft_module-0.0.2.2.dist-info/METADATA
ghent_theft_module-0.0.2.2.dist-info/RECORD
ghent_theft_module-0.0.2.2.dist-info/WHEEL
ghent_theft_module-0.0.2.2.dist-info/entry_points.txt
ghent_theft_module-0.0.2.2.dist-info/top_level.txt
