Metadata-Version: 2.1
Name: ghent-theft-module
Version: 0.0.2.2
Summary: A Python package demonstration.
Home-page: https://github.com/lucassel/ghent-theft-module
Author: Lucas Selfslagh
License: MIT
Platform: UNKNOWN
Classifier: License :: OSI Approved :: MIT License
Classifier: Programming Language :: Python :: 3
Classifier: Programming Language :: Python :: 3.7
